{"version":1,"resource":"vscode-remote://wsl%2Bubuntu-22.04/home/greg/example-app/resources/views/profile/partials/update-profile-information-form.blade.php","entries":[{"id":"0fF7.php","timestamp":1731073188000},{"id":"QcBF.php","timestamp":1731073226940},{"id":"3hPt.php","timestamp":1731073609750},{"id":"tKaO.php","timestamp":1731073645960},{"id":"KiZE.php","source":"undoRedo.source","timestamp":1731085967640},{"id":"5TGr.php","timestamp":1731090683390},{"id":"9SVr.php","timestamp":1731090727380},{"id":"ID6a.php","source":"undoRedo.source","timestamp":1731090735320},{"id":"ymjf.php","source":"undoRedo.source","timestamp":1731090746050},{"id":"8kHr.php","timestamp":1731090890290},{"id":"83hi.php","source":"undoRedo.source","timestamp":1731091067150},{"id":"s8RN.php","timestamp":1731091074570}]}