{"version":1,"resource":"vscode-remote://wsl%2Bubuntu-22.04/home/greg/example-app/resources/views/dashboard.blade.php","entries":[{"id":"GZt7.php","timestamp":1731007736667},{"id":"ULze.php","timestamp":1731007957587},{"id":"Xl2d.php","timestamp":1731007975397},{"id":"qeSl.php","timestamp":1731008098817},{"id":"srRL.php","timestamp":1731008136837},{"id":"g4AP.php","timestamp":1731008147697},{"id":"rWWZ.php","timestamp":1731008381857},{"id":"5z23.php","timestamp":1731008810467},{"id":"bLuu.php","timestamp":1731008993157},{"id":"JEkr.php","timestamp":1731009004107},{"id":"t7XH.php","source":"undoRedo.source","timestamp":1731009008867},{"id":"w5hI.php","timestamp":1731009071637},{"id":"3pND.php","timestamp":1731009091297},{"id":"TVOD.php","timestamp":1731009249687},{"id":"1axQ.php","timestamp":1731009273667},{"id":"QPFv.php","timestamp":1731009545987},{"id":"Ethh.php","timestamp":1731009561187},{"id":"48w3.php","timestamp":1731009604347},{"id":"oRoE.php","source":"undoRedo.source","timestamp":1731009615737},{"id":"eud7.php","timestamp":1731009641047},{"id":"SK49.php","timestamp":1731009661487},{"id":"1iwo.php","source":"undoRedo.source","timestamp":1731009663277},{"id":"U4Vi.php","timestamp":1731009692197},{"id":"eMOX.php","timestamp":1731009723307},{"id":"O4ov.php","timestamp":1731009734307},{"id":"bLLX.php","timestamp":1731009750287},{"id":"3acN.php","timestamp":1731009841467},{"id":"K9rl.php","source":"undoRedo.source","timestamp":1731009848427},{"id":"ekRx.php","timestamp":1731009945417},{"id":"txF3.php","timestamp":1731009982807},{"id":"wmx7.php","timestamp":1731010002727},{"id":"YHAh.php","timestamp":1731010016177},{"id":"6o7v.php","timestamp":1731010039107},{"id":"55Td.php","timestamp":1731010054837},{"id":"Bqbi.php","timestamp":1731010083237},{"id":"GfpW.php","timestamp":1731010095877},{"id":"7sHl.php","timestamp":1731010117107},{"id":"RMPg.php","timestamp":1731010271907},{"id":"xU0g.php","timestamp":1731010307147},{"id":"q6Ta.php","timestamp":1731010813197},{"id":"mH4Y.php","timestamp":1731010829227},{"id":"5STG.php","timestamp":1731011396149},{"id":"tuSt.php","timestamp":1731011429189},{"id":"kcFI.php","timestamp":1731067635210},{"id":"Q94s.php","timestamp":1731067665520},{"id":"iu6q.php","timestamp":1731067700660},{"id":"E8mP.php","timestamp":1731067757110},{"id":"mtUW.php","timestamp":1731067831510},{"id":"yotV.php","source":"undoRedo.source","timestamp":1731067842930},{"id":"QJ5C.php","timestamp":1731067872970}]}